bioplotz/__init__.py
bioplotz/chromosome.py
bioplotz/genecluster.py
bioplotz/manhattan.py
bioplotz/multialign.py
bioplotz-0.1.0.dev22.dist-info/licenses/LICENSE
bioplotz-0.1.0.dev22.dist-info/METADATA
bioplotz-0.1.0.dev22.dist-info/WHEEL
bioplotz-0.1.0.dev22.dist-info/top_level.txt
bioplotz-0.1.0.dev22.dist-info/RECORD
