Metadata-Version: 2.4
Name: bioplotz
Version: 0.1.0.dev22
Summary: A python package for drawing some bioinformatic pictures.
Home-page: https://github.com/sc-zhang/bioplotz
Author: Shengcheng Zhang
Author-email: zsc-zhang@foxmail.com
License-File: LICENSE
Requires-Dist: numpy
Requires-Dist: matplotlib
Requires-Dist: pandas
Dynamic: author
Dynamic: author-email
Dynamic: description
Dynamic: description-content-type
Dynamic: home-page
Dynamic: license-file
Dynamic: requires-dist
Dynamic: summary
